{"nodes": [{"id": "comercial", "label": "comercial.py", "file_type": "code", "source_file": "/home/gk/Projeto-izi/sistema/app/routers/comercial.py", "source_location": "L1"}, {"id": "comercial_health_check", "label": "health_check()", "file_type": "code", "source_file": "/home/gk/Projeto-izi/sistema/app/routers/comercial.py", "source_location": "L19"}, {"id": "comercial_rationale_1", "label": "Router principal do m\u00f3dulo comercial \u2014 Stub de compatibilidade.  Os endpoints fo", "file_type": "rationale", "source_file": "/home/gk/Projeto-izi/sistema/app/routers/comercial.py", "source_location": "L1"}, {"id": "comercial_rationale_20", "label": "Health check do m\u00f3dulo comercial.", "file_type": "rationale", "source_file": "/home/gk/Projeto-izi/sistema/app/routers/comercial.py", "source_location": "L20"}], "edges": [{"source": "comercial", "target": "fastapi", "relation": "imports_from", "confidence": "EXTRACTED", "source_file": "/home/gk/Projeto-izi/sistema/app/routers/comercial.py", "source_location": "L13", "weight": 1.0}, {"source": "comercial", "target": "comercial_health_check", "relation": "contains", "confidence": "EXTRACTED", "source_file": "/home/gk/Projeto-izi/sistema/app/routers/comercial.py", "source_location": "L19", "weight": 1.0}, {"source": "comercial_rationale_1", "target": "comercial", "relation": "rationale_for", "confidence": "EXTRACTED", "source_file": "/home/gk/Projeto-izi/sistema/app/routers/comercial.py", "source_location": "L1", "weight": 1.0}, {"source": "comercial_rationale_20", "target": "comercial_health_check", "relation": "rationale_for", "confidence": "EXTRACTED", "source_file": "/home/gk/Projeto-izi/sistema/app/routers/comercial.py", "source_location": "L20", "weight": 1.0}]}