{"nodes": [{"id": "admin_planos", "label": "admin_planos.py", "file_type": "code", "source_file": "/home/gk/Projeto-izi/sistema/app/routers/admin_planos.py", "source_location": "L1"}, {"id": "admin_planos_listar_modulos", "label": "listar_modulos()", "file_type": "code", "source_file": "/home/gk/Projeto-izi/sistema/app/routers/admin_planos.py", "source_location": "L23"}, {"id": "admin_planos_criar_modulo", "label": "criar_modulo()", "file_type": "code", "source_file": "/home/gk/Projeto-izi/sistema/app/routers/admin_planos.py", "source_location": "L42"}, {"id": "admin_planos_atualizar_modulo", "label": "atualizar_modulo()", "file_type": "code", "source_file": "/home/gk/Projeto-izi/sistema/app/routers/admin_planos.py", "source_location": "L57"}, {"id": "admin_planos_listar_planos", "label": "listar_planos()", "file_type": "code", "source_file": "/home/gk/Projeto-izi/sistema/app/routers/admin_planos.py", "source_location": "L80"}, {"id": "admin_planos_criar_plano", "label": "criar_plano()", "file_type": "code", "source_file": "/home/gk/Projeto-izi/sistema/app/routers/admin_planos.py", "source_location": "L86"}, {"id": "admin_planos_atualizar_plano", "label": "atualizar_plano()", "file_type": "code", "source_file": "/home/gk/Projeto-izi/sistema/app/routers/admin_planos.py", "source_location": "L108"}, {"id": "admin_planos_deletar_plano", "label": "deletar_plano()", "file_type": "code", "source_file": "/home/gk/Projeto-izi/sistema/app/routers/admin_planos.py", "source_location": "L139"}, {"id": "admin_planos_rationale_24", "label": "Lista todos os m\u00f3dulos do sistema. Auto-seeda m\u00f3dulos can\u00f4nicos se tabela vazia.", "file_type": "rationale", "source_file": "/home/gk/Projeto-izi/sistema/app/routers/admin_planos.py", "source_location": "L24"}, {"id": "admin_planos_rationale_45", "label": "Cria um novo m\u00f3dulo do sistema.", "file_type": "rationale", "source_file": "/home/gk/Projeto-izi/sistema/app/routers/admin_planos.py", "source_location": "L45"}, {"id": "admin_planos_rationale_63", "label": "Atualiza um m\u00f3dulo do sistema.", "file_type": "rationale", "source_file": "/home/gk/Projeto-izi/sistema/app/routers/admin_planos.py", "source_location": "L63"}, {"id": "admin_planos_rationale_81", "label": "Lista todos os planos/pacotes dispon\u00edveis.", "file_type": "rationale", "source_file": "/home/gk/Projeto-izi/sistema/app/routers/admin_planos.py", "source_location": "L81"}, {"id": "admin_planos_rationale_89", "label": "Cria um novo plano/pacote com m\u00f3dulos associados.", "file_type": "rationale", "source_file": "/home/gk/Projeto-izi/sistema/app/routers/admin_planos.py", "source_location": "L89"}, {"id": "admin_planos_rationale_114", "label": "Atualiza um plano/pacote e seus m\u00f3dulos associados.", "file_type": "rationale", "source_file": "/home/gk/Projeto-izi/sistema/app/routers/admin_planos.py", "source_location": "L114"}, {"id": "admin_planos_rationale_142", "label": "Exclui um plano/pacote se n\u00e3o estiver vinculado a empresas.", "file_type": "rationale", "source_file": "/home/gk/Projeto-izi/sistema/app/routers/admin_planos.py", "source_location": "L142"}], "edges": [{"source": "admin_planos", "target": "fastapi", "relation": "imports_from", "confidence": "EXTRACTED", "source_file": "/home/gk/Projeto-izi/sistema/app/routers/admin_planos.py", "source_location": "L1", "weight": 1.0}, {"source": "admin_planos", "target": "sqlalchemy_orm", "relation": "imports_from", "confidence": "EXTRACTED", "source_file": "/home/gk/Projeto-izi/sistema/app/routers/admin_planos.py", "source_location": "L2", "weight": 1.0}, {"source": "admin_planos", "target": "typing", "relation": "imports_from", "confidence": "EXTRACTED", "source_file": "/home/gk/Projeto-izi/sistema/app/routers/admin_planos.py", "source_location": "L3", "weight": 1.0}, {"source": "admin_planos", "target": "app_core_database", "relation": "imports_from", "confidence": "EXTRACTED", "source_file": "/home/gk/Projeto-izi/sistema/app/routers/admin_planos.py", "source_location": "L4", "weight": 1.0}, {"source": "admin_planos", "target": "app_core_auth", "relation": "imports_from", "confidence": "EXTRACTED", "source_file": "/home/gk/Projeto-izi/sistema/app/routers/admin_planos.py", "source_location": "L5", "weight": 1.0}, {"source": "admin_planos", "target": "app_models_models", "relation": "imports_from", "confidence": "EXTRACTED", "source_file": "/home/gk/Projeto-izi/sistema/app/routers/admin_planos.py", "source_location": "L6", "weight": 1.0}, {"source": "admin_planos", "target": "app_schemas_plano", "relation": "imports_from", "confidence": "EXTRACTED", "source_file": "/home/gk/Projeto-izi/sistema/app/routers/admin_planos.py", "source_location": "L7", "weight": 1.0}, {"source": "admin_planos", "target": "app_services_seed_modulos", "relation": "imports_from", "confidence": "EXTRACTED", "source_file": "/home/gk/Projeto-izi/sistema/app/routers/admin_planos.py", "source_location": "L15", "weight": 1.0}, {"source": "admin_planos", "target": "admin_planos_listar_modulos", "relation": "contains", "confidence": "EXTRACTED", "source_file": "/home/gk/Projeto-izi/sistema/app/routers/admin_planos.py", "source_location": "L23", "weight": 1.0}, {"source": "admin_planos", "target": "admin_planos_criar_modulo", "relation": "contains", "confidence": "EXTRACTED", "source_file": "/home/gk/Projeto-izi/sistema/app/routers/admin_planos.py", "source_location": "L42", "weight": 1.0}, {"source": "admin_planos", "target": "admin_planos_atualizar_modulo", "relation": "contains", "confidence": "EXTRACTED", "source_file": "/home/gk/Projeto-izi/sistema/app/routers/admin_planos.py", "source_location": "L57", "weight": 1.0}, {"source": "admin_planos", "target": "admin_planos_listar_planos", "relation": "contains", "confidence": "EXTRACTED", "source_file": "/home/gk/Projeto-izi/sistema/app/routers/admin_planos.py", "source_location": "L80", "weight": 1.0}, {"source": "admin_planos", "target": "admin_planos_criar_plano", "relation": "contains", "confidence": "EXTRACTED", "source_file": "/home/gk/Projeto-izi/sistema/app/routers/admin_planos.py", "source_location": "L86", "weight": 1.0}, {"source": "admin_planos", "target": "admin_planos_atualizar_plano", "relation": "contains", "confidence": "EXTRACTED", "source_file": "/home/gk/Projeto-izi/sistema/app/routers/admin_planos.py", "source_location": "L108", "weight": 1.0}, {"source": "admin_planos", "target": "admin_planos_deletar_plano", "relation": "contains", "confidence": "EXTRACTED", "source_file": "/home/gk/Projeto-izi/sistema/app/routers/admin_planos.py", "source_location": "L139", "weight": 1.0}, {"source": "admin_planos_rationale_24", "target": "admin_planos_listar_modulos", "relation": "rationale_for", "confidence": "EXTRACTED", "source_file": "/home/gk/Projeto-izi/sistema/app/routers/admin_planos.py", "source_location": "L24", "weight": 1.0}, {"source": "admin_planos_rationale_45", "target": "admin_planos_criar_modulo", "relation": "rationale_for", "confidence": "EXTRACTED", "source_file": "/home/gk/Projeto-izi/sistema/app/routers/admin_planos.py", "source_location": "L45", "weight": 1.0}, {"source": "admin_planos_rationale_63", "target": "admin_planos_atualizar_modulo", "relation": "rationale_for", "confidence": "EXTRACTED", "source_file": "/home/gk/Projeto-izi/sistema/app/routers/admin_planos.py", "source_location": "L63", "weight": 1.0}, {"source": "admin_planos_rationale_81", "target": "admin_planos_listar_planos", "relation": "rationale_for", "confidence": "EXTRACTED", "source_file": "/home/gk/Projeto-izi/sistema/app/routers/admin_planos.py", "source_location": "L81", "weight": 1.0}, {"source": "admin_planos_rationale_89", "target": "admin_planos_criar_plano", "relation": "rationale_for", "confidence": "EXTRACTED", "source_file": "/home/gk/Projeto-izi/sistema/app/routers/admin_planos.py", "source_location": "L89", "weight": 1.0}, {"source": "admin_planos_rationale_114", "target": "admin_planos_atualizar_plano", "relation": "rationale_for", "confidence": "EXTRACTED", "source_file": "/home/gk/Projeto-izi/sistema/app/routers/admin_planos.py", "source_location": "L114", "weight": 1.0}, {"source": "admin_planos_rationale_142", "target": "admin_planos_deletar_plano", "relation": "rationale_for", "confidence": "EXTRACTED", "source_file": "/home/gk/Projeto-izi/sistema/app/routers/admin_planos.py", "source_location": "L142", "weight": 1.0}]}