{"nodes": [{"id": "client", "label": "client.ts", "file_type": "code", "source_file": "/home/gk/Projeto-izi/context7/packages/sdk/src/client.ts", "source_location": "L1"}, {"id": "client_context7", "label": "Context7", "file_type": "code", "source_file": "/home/gk/Projeto-izi/context7/packages/sdk/src/client.ts", "source_location": "L18"}, {"id": "client_context7_constructor", "label": ".constructor()", "file_type": "code", "source_file": "/home/gk/Projeto-izi/context7/packages/sdk/src/client.ts", "source_location": "L21"}, {"id": "client_context7_searchlibrary", "label": ".searchLibrary()", "file_type": "code", "source_file": "/home/gk/Projeto-izi/context7/packages/sdk/src/client.ts", "source_location": "L81"}, {"id": "client_context7_getcontext", "label": ".getContext()", "file_type": "code", "source_file": "/home/gk/Projeto-izi/context7/packages/sdk/src/client.ts", "source_location": "L124"}], "edges": [{"source": "client", "target": "types", "relation": "imports_from", "confidence": "EXTRACTED", "source_file": "/home/gk/Projeto-izi/context7/packages/sdk/src/client.ts", "source_location": "L1", "weight": 1.0}, {"source": "client", "target": "error", "relation": "imports_from", "confidence": "EXTRACTED", "source_file": "/home/gk/Projeto-izi/context7/packages/sdk/src/client.ts", "source_location": "L8", "weight": 1.0}, {"source": "client", "target": "http", "relation": "imports_from", "confidence": "EXTRACTED", "source_file": "/home/gk/Projeto-izi/context7/packages/sdk/src/client.ts", "source_location": "L9", "weight": 1.0}, {"source": "client", "target": "index", "relation": "imports_from", "confidence": "EXTRACTED", "source_file": "/home/gk/Projeto-izi/context7/packages/sdk/src/client.ts", "source_location": "L10", "weight": 1.0}, {"source": "client", "target": "client_context7", "relation": "contains", "confidence": "EXTRACTED", "source_file": "/home/gk/Projeto-izi/context7/packages/sdk/src/client.ts", "source_location": "L18", "weight": 1.0}, {"source": "client_context7", "target": "client_context7_constructor", "relation": "method", "confidence": "EXTRACTED", "source_file": "/home/gk/Projeto-izi/context7/packages/sdk/src/client.ts", "source_location": "L21", "weight": 1.0}, {"source": "client_context7", "target": "client_context7_searchlibrary", "relation": "method", "confidence": "EXTRACTED", "source_file": "/home/gk/Projeto-izi/context7/packages/sdk/src/client.ts", "source_location": "L81", "weight": 1.0}, {"source": "client_context7", "target": "client_context7_getcontext", "relation": "method", "confidence": "EXTRACTED", "source_file": "/home/gk/Projeto-izi/context7/packages/sdk/src/client.ts", "source_location": "L124", "weight": 1.0}]}